lvmguider/__init__.py
lvmguider/__main__.py
lvmguider/astrometrynet.py
lvmguider/cameras.py
lvmguider/coadd.py
lvmguider/dataclasses.py
lvmguider/extraction.py
lvmguider/focus.py
lvmguider/guider.py
lvmguider/maskbits.py
lvmguider/plotting.py
lvmguider/tools.py
lvmguider/transformations.py
lvmguider/types.py
lvmguider/actor/__init__.py
lvmguider/actor/actor.py
lvmguider/actor/commands/__init__.py
lvmguider/actor/commands/corrections.py
lvmguider/actor/commands/expose.py
lvmguider/actor/commands/focus.py
lvmguider/actor/commands/guide.py
lvmguider/actor/commands/set_pixel.py
lvmguider/actor/commands/status.py
lvmguider/actor/commands/stop.py
lvmguider/etc/datamodel.yml
lvmguider/etc/lvmguider.yml
lvmguider-0.8.1.dist-info/METADATA
lvmguider-0.8.1.dist-info/WHEEL
lvmguider-0.8.1.dist-info/entry_points.txt
lvmguider-0.8.1.dist-info/licenses/LICENSE.md
lvmguider-0.8.1.dist-info/RECORD
