Metadata-Version: 2.4
Name: lvmguider
Version: 0.8.1
Summary: LVM guiding and focusing
Project-URL: Homepage, https://github.com/sdss/lvmguider
Project-URL: Repository, https://github.com/sdss/lvmguider
Project-URL: Documentation, https://lvmguider.readthedocs.org
Author-email: José Sánchez-Gallego <gallegoj@uw.edu>
License: BSD-3-Clause
License-File: LICENSE.md
Requires-Python: <4,>=3.10
Requires-Dist: astropy>=6.0.0; python_version < '3.11'
Requires-Dist: astropy>=7.0.0; python_version >= '3.11'
Requires-Dist: click-default-group>=1.2.2
Requires-Dist: fastparquet>=2023.8.0
Requires-Dist: matplotlib>=3.7.2
Requires-Dist: numpy<2.0.0,>=1.21.0; python_version < '3.11'
Requires-Dist: numpy>=2.0.0; python_version >= '3.11'
Requires-Dist: pandas>=2.0.0
Requires-Dist: peewee>=3.16.3
Requires-Dist: pgpasslib>=1.1.0
Requires-Dist: psycopg2-binary>=2.9.7
Requires-Dist: pyarrow>=18.0.0
Requires-Dist: scipy>=1.10.1
Requires-Dist: sdss-clu>=2.6.0
Requires-Dist: sdsstools>=1.9.5
Requires-Dist: seaborn>=0.13.2
Requires-Dist: sep>=1.4.1
Requires-Dist: simple-pid>=2.0.0
Requires-Dist: typing-extensions>=4.5.0
Requires-Dist: watchdog>=3.0.0
